{
  "schemaVersion": 1,
  "id": "mc-looper",
  "version": "1.0.0",
  "name": "MC Looper",
  "description": "A configurable automation mod with loop-based task execution",
  "authors": [
    "jacqueb"
  ],
  "contact": {
    "homepage": "https://github.com/jacqueb/mc-looper",
    "sources": "https://github.com/jacqueb/mc-looper"
  },
  "license": "MIT",
  "icon": "assets/mclooper/icon.png",
  "environment": "*",
  "entrypoints": {
    "client": [
      "com.jacqueb.mclooper.McLooperMod"
    ]
  },
  "mixins": [],
  "depends": {
    "fabricloader": ">=0.15.7",
    "fabric": "*",
    "minecraft": "1.20.4",
    "java": ">=17"
  },
  "suggests": {
    "modmenu": "*"
  }
}
